monadic/__init__.py
monadic/_version.py
monadic/dict.py
monadic/list.py
monadic/option.py
monadic/py.typed
monadic/result.py
monadic/set.py
monadic/interfaces/__init__.py
monadic/interfaces/iterable.py
monadic/interfaces/maybe.py
monadic/interfaces/monad.py
monadic-0.0.1.dist-info/METADATA
monadic-0.0.1.dist-info/WHEEL
monadic-0.0.1.dist-info/licenses/LICENSE
monadic-0.0.1.dist-info/RECORD
