Metadata-Version: 2.1
Name: monadic
Version: 0.0.1
Summary: Functional programming in Python using Monadic types
Project-URL: Homepage, https://github.com/austinrwarner/monadic
Project-URL: Issues, https://github.com/austinrwarner/monadic/issues
Author-email: Austin Warner <austin.richard.warner@gmail.com>
License-File: LICENSE
Classifier: License :: OSI Approved :: MIT License
Classifier: Operating System :: OS Independent
Classifier: Programming Language :: Python :: 3
Requires-Python: >=3.8
Provides-Extra: docs
Requires-Dist: myst-parser; extra == 'docs'
Requires-Dist: sphinx; extra == 'docs'
Requires-Dist: sphinx-rtd-theme; extra == 'docs'
Provides-Extra: test
Requires-Dist: coverage; extra == 'test'
Requires-Dist: coverage-badge; extra == 'test'
Requires-Dist: pytest; extra == 'test'
Requires-Dist: pytest-console-scripts; extra == 'test'
Requires-Dist: pytest-cov; extra == 'test'
